{
    "treatment_information": [
        {
            "treatment_type": "Not specified",
            "specific_treatment": "Not specified",
            "start_date": "Not specified",
            "end_date": "Not specified",
            "dosage_or_details": "Not specified",
            "treatment_response": "Not specified"
        }
    ],
    "treatment_timeline": [
        {
            "date": "Not specified",
            "event": "Diagnosis of juvenile Tay-Sachs disease by brain biopsy on the older sibling"
        },
        {
            "date": "Not specified",
            "event": "Serum hexosaminidase assays performed on both patients and the parents"
        },
        {
            "date": "Not specified",
            "event": "Patients died at ages 8 and 7, respectively"
        }
    ],
    "patient_outcome": {
        "final_status": "Deceased",
        "follow_up_details": "Not specified",
        "complications": "No complications mentioned",
        "long_term_prognosis": "Not specified",
        "recovery_timeline": "Not specified",
        "quality_of_life": "Not specified",
        "patient_perspective": "Not specified"
    }
}